vowdb/VowDB.py
vowdb/__init__.py
vowdb-0.1.6.dist-info/licenses/LICENSE
vowdb-0.1.6.dist-info/METADATA
vowdb-0.1.6.dist-info/WHEEL
vowdb-0.1.6.dist-info/top_level.txt
vowdb-0.1.6.dist-info/RECORD
