Metadata-Version: 2.4
Name: vowdb
Version: 0.1.6
Summary: A high-performance vector database for fast text similarity search
Home-page: https://github.com/yourusername/vowdb
Author: Your Name
Author-email: Rushikesh Sunil Kotkar <rshksh019@gmail.com>
License: MIT License
Project-URL: Homepage, https://github.com/rushikeshkotkar04/vowdb
Project-URL: Repository, https://github.com/rushikeshkotkar04/vowdb
Classifier: Programming Language :: Python :: 3
Classifier: License :: OSI Approved :: MIT License
Classifier: Operating System :: OS Independent
Requires-Python: >=3.8
License-File: LICENSE
Requires-Dist: faiss-cpu>=1.7.4
Requires-Dist: numpy>=1.21.0
Requires-Dist: psutil>=5.9.0
Dynamic: license-file
